octomap.so
octomap_python-1.8.0.post12.data/data/bin/binvox2bt
octomap_python-1.8.0.post12.data/data/bin/bt2vrml
octomap_python-1.8.0.post12.data/data/bin/compare_octrees
octomap_python-1.8.0.post12.data/data/bin/convert_octree
octomap_python-1.8.0.post12.data/data/bin/edit_octree
octomap_python-1.8.0.post12.data/data/bin/eval_octree_accuracy
octomap_python-1.8.0.post12.data/data/bin/graph2tree
octomap_python-1.8.0.post12.data/data/bin/log2graph
octomap_python-1.8.0.post12.data/data/include/dynamicEDT3D/bucketedqueue.h
octomap_python-1.8.0.post12.data/data/include/dynamicEDT3D/bucketedqueue.hxx
octomap_python-1.8.0.post12.data/data/include/dynamicEDT3D/dynamicEDT3D.h
octomap_python-1.8.0.post12.data/data/include/dynamicEDT3D/dynamicEDTOctomap.h
octomap_python-1.8.0.post12.data/data/include/dynamicEDT3D/point.h
octomap_python-1.8.0.post12.data/data/include/octomap/AbstractOcTree.h
octomap_python-1.8.0.post12.data/data/include/octomap/AbstractOccupancyOcTree.h
octomap_python-1.8.0.post12.data/data/include/octomap/ColorOcTree.h
octomap_python-1.8.0.post12.data/data/include/octomap/CountingOcTree.h
octomap_python-1.8.0.post12.data/data/include/octomap/MCTables.h
octomap_python-1.8.0.post12.data/data/include/octomap/MapCollection.h
octomap_python-1.8.0.post12.data/data/include/octomap/MapCollection.hxx
octomap_python-1.8.0.post12.data/data/include/octomap/MapNode.h
octomap_python-1.8.0.post12.data/data/include/octomap/MapNode.hxx
octomap_python-1.8.0.post12.data/data/include/octomap/OcTree.h
octomap_python-1.8.0.post12.data/data/include/octomap/OcTreeBase.h
octomap_python-1.8.0.post12.data/data/include/octomap/OcTreeBaseImpl.h
octomap_python-1.8.0.post12.data/data/include/octomap/OcTreeBaseImpl.hxx
octomap_python-1.8.0.post12.data/data/include/octomap/OcTreeDataNode.h
octomap_python-1.8.0.post12.data/data/include/octomap/OcTreeDataNode.hxx
octomap_python-1.8.0.post12.data/data/include/octomap/OcTreeIterator.hxx
octomap_python-1.8.0.post12.dist-info/METADATA
octomap_python-1.8.0.post12.dist-info/RECORD
octomap_python-1.8.0.post12.dist-info/WHEEL
octomap_python-1.8.0.post12.dist-info/top_level.txt
