Metadata-Version: 2.1
Name: octomap-python
Version: 1.8.0.post12
Summary: Python binding of the OctoMap library.
Home-page: https://github.com/wkentaro/octomap-python
Maintainer: Kentaro Wada
Maintainer-email: www.kentaro.wada@gmail.com
License: BSD
Platform: UNKNOWN
Classifier: Development Status :: 5 - Production/Stable
Classifier: Intended Audience :: Developers
Classifier: Natural Language :: English
Classifier: Programming Language :: Python
Classifier: Programming Language :: Python :: 2
Classifier: Programming Language :: Python :: 3
Classifier: Programming Language :: Python :: Implementation :: CPython
Classifier: Programming Language :: Python :: Implementation :: PyPy
Provides-Extra: example
Requires-Dist: numpy
Provides-Extra: example
Requires-Dist: glooey; extra == 'example'
Requires-Dist: imgviz; extra == 'example'
Requires-Dist: pyglet; extra == 'example'
Requires-Dist: trimesh[easy]; extra == 'example'
